{
  "id": "udyr-skin10-mat-stance01",
  "name": "Udyr Skin10 Mat Stance01",
  "category": "body",
  "version": 1,
  "updatedAt": "2026-04-17T18:02:43.684Z",
  "description": "",
  "userSlots": [
    {
      "name": "Diffuse_Texture",
      "kind": "diffuse",
      "description": ""
    }
  ],
  "materialName": "jadelib_udyr_skin10_mat_stance01",
  "textureFiles": [
    {
      "name": "black.SKINS_Lissandra_Skin43.tex",
      "updatedAt": "2026-04-17T18:02:43.678Z"
    },
    {
      "name": "black.SKINS_Lissandra_Skin43.tex",
      "updatedAt": "2026-04-17T18:02:43.678Z"
    },
    {
      "name": "black.SKINS_Lissandra_Skin43.tex",
      "updatedAt": "2026-04-17T18:02:43.678Z"
    },
    {
      "name": "black.SKINS_Lissandra_Skin43.tex",
      "updatedAt": "2026-04-17T18:02:43.678Z"
    },
    {
      "name": "Udyr_Skin06_MT_Color.tex",
      "updatedAt": "2026-04-17T18:02:43.678Z"
    },
    {
      "name": "Udyr_Skin10_Submesh_Scroll001.tex",
      "updatedAt": "2026-04-17T18:02:43.678Z"
    },
    {
      "name": "Udyr_Skin06_MT_Color.tex",
      "updatedAt": "2026-04-17T18:02:43.678Z"
    },
    {
      "name": "black.SKINS_Lissandra_Skin43.tex",
      "updatedAt": "2026-04-17T18:02:43.678Z"
    }
  ],
  "snippetFile": "snippet.txt",
  "source": {
    "champion": "Udyr",
    "skin": "skin10",
    "bin": "data/characters/udyr/skins/skin10.bin",
    "entryKey": "Characters/Udyr/Skins/Skin10/Materials/Udyr_Skin10_Mat_Stance01"
  },
  "usedBy": [
    {
      "champion": "Udyr",
      "skin": "skin10",
      "bin": "data/characters/udyr/skins/skin10.bin"
    }
  ]
}