{
  "id": "blitzcrank-skin67-hand-tube-red",
  "name": "Blitzcrank Skin67 Hand Tube Red",
  "category": "body",
  "version": 1,
  "updatedAt": "2026-04-17T17:12:11.927Z",
  "description": "",
  "userSlots": [
    {
      "name": "Diffuse_Texture",
      "kind": "diffuse",
      "description": ""
    }
  ],
  "materialName": "jadelib_blitzcrank_skin67_hand_tube_red",
  "textureFiles": [
    {
      "name": "black.SKINS_Lissandra_Skin43.tex",
      "updatedAt": "2026-04-17T17:12:11.921Z"
    },
    {
      "name": "black.SKINS_Lissandra_Skin43.tex",
      "updatedAt": "2026-04-17T17:12:11.921Z"
    },
    {
      "name": "black.SKINS_Lissandra_Skin43.tex",
      "updatedAt": "2026-04-17T17:12:11.921Z"
    },
    {
      "name": "black.SKINS_Lissandra_Skin43.tex",
      "updatedAt": "2026-04-17T17:12:11.921Z"
    },
    {
      "name": "Blitzcrank_Skin67_HandRed_TX_CM.Chroma_Blitzcrank_AprilFools.tex",
      "updatedAt": "2026-04-17T17:12:11.921Z"
    },
    {
      "name": "white.tex",
      "updatedAt": "2026-04-17T17:12:11.921Z"
    },
    {
      "name": "white.tex",
      "updatedAt": "2026-04-17T17:12:11.921Z"
    },
    {
      "name": "black.SKINS_Lissandra_Skin43.tex",
      "updatedAt": "2026-04-17T17:12:11.921Z"
    }
  ],
  "snippetFile": "snippet.txt",
  "source": {
    "champion": "Blitzcrank",
    "skin": "skin67",
    "bin": "data/characters/blitzcrank/skins/skin67.bin",
    "entryKey": "Characters/Blitzcrank/Skins/Skin67/Materials/Blitzcrank_Skin67_HandTubeRed"
  },
  "usedBy": [
    {
      "champion": "Blitzcrank",
      "skin": "skin67",
      "bin": "data/characters/blitzcrank/skins/skin67.bin"
    }
  ]
}