{
  "id": "mat-nasus-skin29-goop-inst",
  "name": "Mat Nasus Skin29 Goop Inst",
  "category": "body",
  "version": 1,
  "updatedAt": "2026-04-17T17:41:44.717Z",
  "description": "",
  "userSlots": [
    {
      "name": "Diffuse_Texture",
      "kind": "diffuse",
      "description": ""
    }
  ],
  "materialName": "jadelib_mat_nasus_skin29_goop_inst",
  "textureFiles": [
    {
      "name": "Nasus_Skin29_Matcap_Nasus_Goop.tex",
      "updatedAt": "2026-04-17T17:41:44.711Z"
    },
    {
      "name": "white.tex",
      "updatedAt": "2026-04-17T17:41:44.711Z"
    }
  ],
  "snippetFile": "snippet.txt",
  "source": {
    "champion": "Nasus",
    "skin": "skin29",
    "bin": "data/characters/nasus/skins/skin29.bin",
    "entryKey": "Characters/Nasus/Skins/Skin29/Materials/Mat_Nasus_Skin29_Goop_inst"
  },
  "usedBy": [
    {
      "champion": "Nasus",
      "skin": "skin29",
      "bin": "data/characters/nasus/skins/skin29.bin"
    }
  ]
}