{
  "id": "hkg-mat-cap-translucent-jelly-bear-inst",
  "name": "Hkg Mat Cap Translucent Jelly Bear Inst",
  "category": "toon",
  "version": 1,
  "updatedAt": "2026-04-17T17:08:59.407Z",
  "description": "",
  "userSlots": [
    {
      "name": "Diffuse_Texture",
      "kind": "diffuse",
      "description": ""
    }
  ],
  "materialName": "jadelib_hkg_mat_cap_translucent_jelly_bear_inst",
  "textureFiles": [
    {
      "name": "Annie_Skin22_TibbersApple_MC.tex",
      "updatedAt": "2026-04-17T17:08:59.401Z"
    },
    {
      "name": "Annie_Skin22_TibbersTransCol.tex",
      "updatedAt": "2026-04-17T17:08:59.401Z"
    },
    {
      "name": "black.SKINS_Lissandra_Skin43.tex",
      "updatedAt": "2026-04-17T17:08:59.401Z"
    }
  ],
  "snippetFile": "snippet.txt",
  "source": {
    "champion": "Annie",
    "skin": "skin22",
    "bin": "data/characters/annie/skins/skin22.bin",
    "entryKey": "Characters/Annie/Skins/Skin22/Materials/HKG_MatCap_Translucent_Jelly_Bear_inst"
  },
  "usedBy": [
    {
      "champion": "Annie",
      "skin": "skin22",
      "bin": "data/characters/annie/skins/skin22.bin"
    }
  ]
}