{
  "id": "specular-fresnel-masked-inst",
  "name": "Specular Fresnel Masked Inst",
  "category": "glow",
  "version": 1,
  "updatedAt": "2026-04-17T17:27:08.098Z",
  "description": "",
  "userSlots": [],
  "materialName": "jadelib_specular_fresnel_masked_inst",
  "textureFiles": [
    {
      "name": "KalistaAltar_Skin24_TX_CM.SKINS_Kalista_Skin24.tex",
      "updatedAt": "2026-04-17T17:27:08.093Z"
    },
    {
      "name": "Kalista_Skin24_Spear_Mat.SKINS_Kalista_Skin24.tex",
      "updatedAt": "2026-04-17T17:27:08.093Z"
    },
    {
      "name": "Default_Gradient.tex",
      "updatedAt": "2026-04-17T17:27:08.093Z"
    }
  ],
  "snippetFile": "snippet.txt",
  "source": {
    "champion": "Kalista",
    "skin": "skin24",
    "bin": "data/characters/kalistaaltar/skins/skin24.bin",
    "entryKey": "Characters/KalistaAltar/Skins/Skin24/Materials/Specular_Fresnel_Masked_inst"
  },
  "usedBy": [
    {
      "champion": "Kalista",
      "skin": "skin24",
      "bin": "data/characters/kalistaaltar/skins/skin24.bin"
    }
  ]
}